dpti
dpti/dags
dpti/lib
