Metadata-Version: 2.1
Name: dpti
Version: 0.1.3
Summary: Python dpti for thermodynamics integration
Home-page: UNKNOWN
Author: Deep Modeling Team
Author-email: 
License: UNKNOWN
Keywords: free energy thermodynamics integration deepmd-kit
Platform: UNKNOWN
Classifier: Programming Language :: Python :: 3.6
Classifier: License :: OSI Approved :: GNU Lesser General Public License v3 (LGPLv3)
Requires-Python: >3.6
